{"v2.2": {"description": "Multi-Domain Wizard-of-Oz dataset (MultiWOZ), a fully-labeled collection of human-human written conversations spanning over multiple domains and topics.\nMultiWOZ 2.1 (Eric et al., 2019) identified and fixed many erroneous annotations and user utterances in the original version, resulting in an\nimproved version of the dataset. MultiWOZ 2.2 is a yet another improved version of this dataset, which identifies and fizes dialogue state annotation errors\nacross 17.3% of the utterances on top of MultiWOZ 2.1 and redefines the ontology by disallowing vocabularies of slots with a large number of possible values\n(e.g., restaurant name, time of booking) and introducing standardized slot span annotations for these slots.\n", "citation": "@article{corr/abs-2007-12720,\n  author    = {Xiaoxue Zang and\n               Abhinav Rastogi and\n               Srinivas Sunkara and\n               Raghav Gupta and\n               Jianguo Zhang and\n               Jindong Chen},\n  title     = {MultiWOZ 2.2 : {A} Dialogue Dataset with Additional Annotation Corrections\n               and State Tracking Baselines},\n  journal   = {CoRR},\n  volume    = {abs/2007.12720},\n  year      = {2020},\n  url       = {https://arxiv.org/abs/2007.12720},\n  archivePrefix = {arXiv},\n  eprint    = {2007.12720}\n}\n", "homepage": "https://github.com/budzianowski/multiwoz/tree/master/data/MultiWOZ_2.2", "license": "Apache License 2.0", "features": {"dialogue_id": {"dtype": "string", "id": null, "_type": "Value"}, "services": {"feature": {"dtype": "string", "id": null, "_type": "Value"}, "length": -1, "id": null, "_type": "Sequence"}, "turns": {"feature": {"turn_id": {"dtype": "string", "id": null, "_type": "Value"}, "speaker": {"num_classes": 2, "names": ["USER", "SYSTEM"], "names_file": null, "id": null, "_type": "ClassLabel"}, "utterance": {"dtype": "string", "id": null, "_type": "Value"}, "frames": {"feature": {"service": {"dtype": "string", "id": null, "_type": "Value"}, "state": {"active_intent": {"dtype": "string", "id": null, "_type": "Value"}, "requested_slots": {"feature": {"dtype": "string", "id": null, "_type": "Value"}, "length": -1, "id": null, "_type": "Sequence"}, "slots_values": {"feature": {"slots_values_name": {"dtype": "string", "id": null, "_type": "Value"}, "slots_values_list": {"feature": {"dtype": "string", "id": null, "_type": "Value"}, "length": -1, "id": null, "_type": "Sequence"}}, "length": -1, "id": null, "_type": "Sequence"}}, "slots": {"feature": {"slot": {"dtype": "string", "id": null, "_type": "Value"}, "value": {"dtype": "string", "id": null, "_type": "Value"}, "start": {"dtype": "int32", "id": null, "_type": "Value"}, "exclusive_end": {"dtype": "int32", "id": null, "_type": "Value"}, "copy_from": {"dtype": "string", "id": null, "_type": "Value"}, "copy_from_value": {"feature": {"dtype": "string", "id": null, "_type": "Value"}, "length": -1, "id": null, "_type": "Sequence"}}, "length": -1, "id": null, "_type": "Sequence"}}, "length": -1, "id": null, "_type": "Sequence"}, "dialogue_acts": {"dialog_act": {"feature": {"act_type": {"dtype": "string", "id": null, "_type": "Value"}, "act_slots": {"feature": {"slot_name": {"dtype": "string", "id": null, "_type": "Value"}, "slot_value": {"dtype": "string", "id": null, "_type": "Value"}}, "length": -1, "id": null, "_type": "Sequence"}}, "length": -1, "id": null, "_type": "Sequence"}, "span_info": {"feature": {"act_type": {"dtype": "string", "id": null, "_type": "Value"}, "act_slot_name": {"dtype": "string", "id": null, "_type": "Value"}, "act_slot_value": {"dtype": "string", "id": null, "_type": "Value"}, "span_start": {"dtype": "int32", "id": null, "_type": "Value"}, "span_end": {"dtype": "int32", "id": null, "_type": "Value"}}, "length": -1, "id": null, "_type": "Sequence"}}}, "length": -1, "id": null, "_type": "Sequence"}}, "post_processed": null, "supervised_keys": null, "builder_name": "multi_woz_v22", "config_name": "v2.2", "version": {"version_str": "2.2.0", "description": null, "major": 2, "minor": 2, "patch": 0}, "splits": {"train": {"name": "train", "num_bytes": 68636165, "num_examples": 8438, "dataset_name": "multi_woz_v22"}, "validation": {"name": "validation", "num_bytes": 9048022, "num_examples": 1000, "dataset_name": "multi_woz_v22"}, "test": {"name": "test", "num_bytes": 9079287, "num_examples": 1000, "dataset_name": "multi_woz_v22"}}, "download_checksums": {"https://github.com/budzianowski/multiwoz/raw/master/data/MultiWOZ_2.2/dialog_acts.json": {"num_bytes": 62353862, "checksum": "cec7a6ed7cda1547ffeaef83bbbe14007cf1d6a2effc354925f4e18bd36eede3"}, "https://github.com/budzianowski/multiwoz/raw/master/data/MultiWOZ_2.2/train/dialogues_001.json": {"num_bytes": 10678915, "checksum": "2d1a5d92bb5ea1a6017f416f76b43e11bdad945b1f93acf870f2f671a98c3032"}, "https://github.com/budzianowski/multiwoz/raw/master/data/MultiWOZ_2.2/train/dialogues_002.json": {"num_bytes": 10779713, "checksum": "2f3ea771d4e01cb2780357738cff7f7496b87d34c221cc240df74501312438d3"}, "https://github.com/budzianowski/multiwoz/raw/master/data/MultiWOZ_2.2/train/dialogues_003.json": {"num_bytes": 9980185, "checksum": "74f73311936c7b4928b073698e5ea61dedad009dc45672963735684e1279521a"}, "https://github.com/budzianowski/multiwoz/raw/master/data/MultiWOZ_2.2/train/dialogues_004.json": {"num_bytes": 10268501, "checksum": "2f9f18b6cb0abbc58c86ca9291aa19baf80395521f9556cf02189c698c48bc52"}, "https://github.com/budzianowski/multiwoz/raw/master/data/MultiWOZ_2.2/train/dialogues_005.json": {"num_bytes": 10519111, "checksum": "eedbe5c649072a3c163e8da109f3c3fd0502425c63db584a11a9cadaa09c91db"}, "https://github.com/budzianowski/multiwoz/raw/master/data/MultiWOZ_2.2/train/dialogues_006.json": {"num_bytes": 10567892, "checksum": "2a51cfed1224110e4cdce80b051d3f7ebecd223d0b3d1c4ade0dd8fc484675fe"}, "https://github.com/budzianowski/multiwoz/raw/master/data/MultiWOZ_2.2/train/dialogues_007.json": {"num_bytes": 10369619, "checksum": "e062becf19b670a45b9333390b6a72f93fc2ed436371ba342499e6532912b1f3"}, "https://github.com/budzianowski/multiwoz/raw/master/data/MultiWOZ_2.2/train/dialogues_008.json": {"num_bytes": 10207590, "checksum": "9cd73cfae130e4d8c76854b6c0f393d68fb084f665a1c7527e04e3b26f877d1b"}, "https://github.com/budzianowski/multiwoz/raw/master/data/MultiWOZ_2.2/train/dialogues_009.json": {"num_bytes": 10169150, "checksum": "fff3f55ee9bd8ecc2492cdb8101e3d5908705e4edd65b3e8cbd7a825be18e47e"}, "https://github.com/budzianowski/multiwoz/raw/master/data/MultiWOZ_2.2/train/dialogues_010.json": {"num_bytes": 10539115, "checksum": "628db438d4f6ab62fb849d3e9df264845b921961052c19b336c8853e2bf4e8d8"}, "https://github.com/budzianowski/multiwoz/raw/master/data/MultiWOZ_2.2/train/dialogues_011.json": {"num_bytes": 10326640, "checksum": "82e2d2900a037b866a01d05974734dd419e89b329fe29ef93b35eea96d27feb8"}, "https://github.com/budzianowski/multiwoz/raw/master/data/MultiWOZ_2.2/train/dialogues_012.json": {"num_bytes": 10585038, "checksum": "5b18461e0f3ff0698818e02a2e105f4f25727d88d02cc4706de19d138e9ceba0"}, "https://github.com/budzianowski/multiwoz/raw/master/data/MultiWOZ_2.2/train/dialogues_013.json": {"num_bytes": 10471561, "checksum": "0f90ba730400be770f753fc46e868189709e6ce06e97d780843ed09db16762b4"}, "https://github.com/budzianowski/multiwoz/raw/master/data/MultiWOZ_2.2/train/dialogues_014.json": {"num_bytes": 10261423, "checksum": "7bd668216f43f6713232c07dcaa1d84e490eeee15caa1b3d843c3075d4b84a10"}, "https://github.com/budzianowski/multiwoz/raw/master/data/MultiWOZ_2.2/train/dialogues_015.json": {"num_bytes": 10423554, "checksum": "5f551d134860595e7834eedab3ebe16e277953cc81b29f46104ef3070cddd4ac"}, "https://github.com/budzianowski/multiwoz/raw/master/data/MultiWOZ_2.2/train/dialogues_016.json": {"num_bytes": 10218789, "checksum": "22eeed01c15a4fba6ac395a6708400672c5c07dbfbd6448bcb451f8697324881"}, "https://github.com/budzianowski/multiwoz/raw/master/data/MultiWOZ_2.2/train/dialogues_017.json": {"num_bytes": 5020437, "checksum": "a1dba37c0fd1dba519500b57be0384219dd4a7bacaec94e124d431932724bd8d"}, "https://github.com/budzianowski/multiwoz/raw/master/data/MultiWOZ_2.2/dev/dialogues_001.json": {"num_bytes": 11772283, "checksum": "e42bf1839d0ef2b40800b4a82c59924e0d1b6d86dfda84d6405bbe39682a968f"}, "https://github.com/budzianowski/multiwoz/raw/master/data/MultiWOZ_2.2/dev/dialogues_002.json": {"num_bytes": 10708953, "checksum": "b9fe16f495dfc35b6e7a54a8d229cbadcb28f0551fb9596780763e3aa5edeecb"}, "https://github.com/budzianowski/multiwoz/raw/master/data/MultiWOZ_2.2/test/dialogues_001.json": {"num_bytes": 11782790, "checksum": "76921f325905886fafcc6c4ff62c238c48ee8e456a3888c5d8296ff5493f6bb3"}, "https://github.com/budzianowski/multiwoz/raw/master/data/MultiWOZ_2.2/test/dialogues_002.json": {"num_bytes": 10772014, "checksum": "69bd9b0c8a5650d3dcd70eac16148ac6b27c43d7c3c989aa8b53d08241749771"}}, "download_size": 278777135, "post_processing_size": null, "dataset_size": 86763474, "size_in_bytes": 365540609}, "v2.2_active_only": {"description": "Multi-Domain Wizard-of-Oz dataset (MultiWOZ), a fully-labeled collection of human-human written conversations spanning over multiple domains and topics.\nMultiWOZ 2.1 (Eric et al., 2019) identified and fixed many erroneous annotations and user utterances in the original version, resulting in an\nimproved version of the dataset. MultiWOZ 2.2 is a yet another improved version of this dataset, which identifies and fizes dialogue state annotation errors\nacross 17.3% of the utterances on top of MultiWOZ 2.1 and redefines the ontology by disallowing vocabularies of slots with a large number of possible values\n(e.g., restaurant name, time of booking) and introducing standardized slot span annotations for these slots.\n", "citation": "@article{corr/abs-2007-12720,\n  author    = {Xiaoxue Zang and\n               Abhinav Rastogi and\n               Srinivas Sunkara and\n               Raghav Gupta and\n               Jianguo Zhang and\n               Jindong Chen},\n  title     = {MultiWOZ 2.2 : {A} Dialogue Dataset with Additional Annotation Corrections\n               and State Tracking Baselines},\n  journal   = {CoRR},\n  volume    = {abs/2007.12720},\n  year      = {2020},\n  url       = {https://arxiv.org/abs/2007.12720},\n  archivePrefix = {arXiv},\n  eprint    = {2007.12720}\n}\n", "homepage": "https://github.com/budzianowski/multiwoz/tree/master/data/MultiWOZ_2.2", "license": "Apache License 2.0", "features": {"dialogue_id": {"dtype": "string", "id": null, "_type": "Value"}, "services": {"feature": {"dtype": "string", "id": null, "_type": "Value"}, "length": -1, "id": null, "_type": "Sequence"}, "turns": {"feature": {"turn_id": {"dtype": "string", "id": null, "_type": "Value"}, "speaker": {"num_classes": 2, "names": ["USER", "SYSTEM"], "names_file": null, "id": null, "_type": "ClassLabel"}, "utterance": {"dtype": "string", "id": null, "_type": "Value"}, "frames": {"feature": {"service": {"dtype": "string", "id": null, "_type": "Value"}, "state": {"active_intent": {"dtype": "string", "id": null, "_type": "Value"}, "requested_slots": {"feature": {"dtype": "string", "id": null, "_type": "Value"}, "length": -1, "id": null, "_type": "Sequence"}, "slots_values": {"feature": {"slots_values_name": {"dtype": "string", "id": null, "_type": "Value"}, "slots_values_list": {"feature": {"dtype": "string", "id": null, "_type": "Value"}, "length": -1, "id": null, "_type": "Sequence"}}, "length": -1, "id": null, "_type": "Sequence"}}, "slots": {"feature": {"slot": {"dtype": "string", "id": null, "_type": "Value"}, "value": {"dtype": "string", "id": null, "_type": "Value"}, "start": {"dtype": "int32", "id": null, "_type": "Value"}, "exclusive_end": {"dtype": "int32", "id": null, "_type": "Value"}, "copy_from": {"dtype": "string", "id": null, "_type": "Value"}, "copy_from_value": {"feature": {"dtype": "string", "id": null, "_type": "Value"}, "length": -1, "id": null, "_type": "Sequence"}}, "length": -1, "id": null, "_type": "Sequence"}}, "length": -1, "id": null, "_type": "Sequence"}, "dialogue_acts": {"dialog_act": {"feature": {"act_type": {"dtype": "string", "id": null, "_type": "Value"}, "act_slots": {"feature": {"slot_name": {"dtype": "string", "id": null, "_type": "Value"}, "slot_value": {"dtype": "string", "id": null, "_type": "Value"}}, "length": -1, "id": null, "_type": "Sequence"}}, "length": -1, "id": null, "_type": "Sequence"}, "span_info": {"feature": {"act_type": {"dtype": "string", "id": null, "_type": "Value"}, "act_slot_name": {"dtype": "string", "id": null, "_type": "Value"}, "act_slot_value": {"dtype": "string", "id": null, "_type": "Value"}, "span_start": {"dtype": "int32", "id": null, "_type": "Value"}, "span_end": {"dtype": "int32", "id": null, "_type": "Value"}}, "length": -1, "id": null, "_type": "Sequence"}}}, "length": -1, "id": null, "_type": "Sequence"}}, "post_processed": null, "supervised_keys": null, "builder_name": "multi_woz_v22", "config_name": "v2.2_active_only", "version": {"version_str": "2.2.0", "description": null, "major": 2, "minor": 2, "patch": 0}, "splits": {"train": {"name": "train", "num_bytes": 41502206, "num_examples": 8438, "dataset_name": "multi_woz_v22"}, "validation": {"name": "validation", "num_bytes": 5454696, "num_examples": 1000, "dataset_name": "multi_woz_v22"}, "test": {"name": "test", "num_bytes": 5482509, "num_examples": 1000, "dataset_name": "multi_woz_v22"}}, "download_checksums": {"https://github.com/budzianowski/multiwoz/raw/master/data/MultiWOZ_2.2/dialog_acts.json": {"num_bytes": 62353862, "checksum": "cec7a6ed7cda1547ffeaef83bbbe14007cf1d6a2effc354925f4e18bd36eede3"}, "https://github.com/budzianowski/multiwoz/raw/master/data/MultiWOZ_2.2/train/dialogues_001.json": {"num_bytes": 10678915, "checksum": "2d1a5d92bb5ea1a6017f416f76b43e11bdad945b1f93acf870f2f671a98c3032"}, "https://github.com/budzianowski/multiwoz/raw/master/data/MultiWOZ_2.2/train/dialogues_002.json": {"num_bytes": 10779713, "checksum": "2f3ea771d4e01cb2780357738cff7f7496b87d34c221cc240df74501312438d3"}, "https://github.com/budzianowski/multiwoz/raw/master/data/MultiWOZ_2.2/train/dialogues_003.json": {"num_bytes": 9980185, "checksum": "74f73311936c7b4928b073698e5ea61dedad009dc45672963735684e1279521a"}, "https://github.com/budzianowski/multiwoz/raw/master/data/MultiWOZ_2.2/train/dialogues_004.json": {"num_bytes": 10268501, "checksum": "2f9f18b6cb0abbc58c86ca9291aa19baf80395521f9556cf02189c698c48bc52"}, "https://github.com/budzianowski/multiwoz/raw/master/data/MultiWOZ_2.2/train/dialogues_005.json": {"num_bytes": 10519111, "checksum": "eedbe5c649072a3c163e8da109f3c3fd0502425c63db584a11a9cadaa09c91db"}, "https://github.com/budzianowski/multiwoz/raw/master/data/MultiWOZ_2.2/train/dialogues_006.json": {"num_bytes": 10567892, "checksum": "2a51cfed1224110e4cdce80b051d3f7ebecd223d0b3d1c4ade0dd8fc484675fe"}, "https://github.com/budzianowski/multiwoz/raw/master/data/MultiWOZ_2.2/train/dialogues_007.json": {"num_bytes": 10369619, "checksum": "e062becf19b670a45b9333390b6a72f93fc2ed436371ba342499e6532912b1f3"}, "https://github.com/budzianowski/multiwoz/raw/master/data/MultiWOZ_2.2/train/dialogues_008.json": {"num_bytes": 10207590, "checksum": "9cd73cfae130e4d8c76854b6c0f393d68fb084f665a1c7527e04e3b26f877d1b"}, "https://github.com/budzianowski/multiwoz/raw/master/data/MultiWOZ_2.2/train/dialogues_009.json": {"num_bytes": 10169150, "checksum": "fff3f55ee9bd8ecc2492cdb8101e3d5908705e4edd65b3e8cbd7a825be18e47e"}, "https://github.com/budzianowski/multiwoz/raw/master/data/MultiWOZ_2.2/train/dialogues_010.json": {"num_bytes": 10539115, "checksum": "628db438d4f6ab62fb849d3e9df264845b921961052c19b336c8853e2bf4e8d8"}, "https://github.com/budzianowski/multiwoz/raw/master/data/MultiWOZ_2.2/train/dialogues_011.json": {"num_bytes": 10326640, "checksum": "82e2d2900a037b866a01d05974734dd419e89b329fe29ef93b35eea96d27feb8"}, "https://github.com/budzianowski/multiwoz/raw/master/data/MultiWOZ_2.2/train/dialogues_012.json": {"num_bytes": 10585038, "checksum": "5b18461e0f3ff0698818e02a2e105f4f25727d88d02cc4706de19d138e9ceba0"}, "https://github.com/budzianowski/multiwoz/raw/master/data/MultiWOZ_2.2/train/dialogues_013.json": {"num_bytes": 10471561, "checksum": "0f90ba730400be770f753fc46e868189709e6ce06e97d780843ed09db16762b4"}, "https://github.com/budzianowski/multiwoz/raw/master/data/MultiWOZ_2.2/train/dialogues_014.json": {"num_bytes": 10261423, "checksum": "7bd668216f43f6713232c07dcaa1d84e490eeee15caa1b3d843c3075d4b84a10"}, "https://github.com/budzianowski/multiwoz/raw/master/data/MultiWOZ_2.2/train/dialogues_015.json": {"num_bytes": 10423554, "checksum": "5f551d134860595e7834eedab3ebe16e277953cc81b29f46104ef3070cddd4ac"}, "https://github.com/budzianowski/multiwoz/raw/master/data/MultiWOZ_2.2/train/dialogues_016.json": {"num_bytes": 10218789, "checksum": "22eeed01c15a4fba6ac395a6708400672c5c07dbfbd6448bcb451f8697324881"}, "https://github.com/budzianowski/multiwoz/raw/master/data/MultiWOZ_2.2/train/dialogues_017.json": {"num_bytes": 5020437, "checksum": "a1dba37c0fd1dba519500b57be0384219dd4a7bacaec94e124d431932724bd8d"}, "https://github.com/budzianowski/multiwoz/raw/master/data/MultiWOZ_2.2/dev/dialogues_001.json": {"num_bytes": 11772283, "checksum": "e42bf1839d0ef2b40800b4a82c59924e0d1b6d86dfda84d6405bbe39682a968f"}, "https://github.com/budzianowski/multiwoz/raw/master/data/MultiWOZ_2.2/dev/dialogues_002.json": {"num_bytes": 10708953, "checksum": "b9fe16f495dfc35b6e7a54a8d229cbadcb28f0551fb9596780763e3aa5edeecb"}, "https://github.com/budzianowski/multiwoz/raw/master/data/MultiWOZ_2.2/test/dialogues_001.json": {"num_bytes": 11782790, "checksum": "76921f325905886fafcc6c4ff62c238c48ee8e456a3888c5d8296ff5493f6bb3"}, "https://github.com/budzianowski/multiwoz/raw/master/data/MultiWOZ_2.2/test/dialogues_002.json": {"num_bytes": 10772014, "checksum": "69bd9b0c8a5650d3dcd70eac16148ac6b27c43d7c3c989aa8b53d08241749771"}}, "download_size": 278777135, "post_processing_size": null, "dataset_size": 52439411, "size_in_bytes": 331216546}}