{"squad_kor_v2": {"description": "KorQuAD 2.0 is a Korean question and answering dataset consisting of a total of 100,000+ pairs. There are three major differences from KorQuAD 1.0, which is the standard Korean Q & A data. The first is that a given document is a whole Wikipedia page, not just one or two paragraphs. Second, because the document also contains tables and lists, it is necessary to understand the document structured with HTML tags. Finally, the answer can be a long text covering not only word or phrase units, but paragraphs, tables, and lists. As a baseline model, BERT Multilingual is used, released by Google as an open source. It shows 46.0% F1 score, a very low score compared to 85.7% of the human F1 score. It indicates that this data is a challenging task. Additionally, we increased the performance by no-answer data augmentation. Through the distribution of this data, we intend to extend the limit of MRC that was limited to plain text to real world tasks of various lengths and formats.\n", "citation": "@article{NODE09353166,\n    author={Youngmin Kim,Seungyoung Lim;Hyunjeong Lee;Soyoon Park;Myungji Kim},\n    title={{KorQuAD 2.0: Korean QA Dataset for Web Document Machine Comprehension}},\n    booltitle={{Journal of KIISE \uc81c47\uad8c \uc81c6\ud638}},\n    journal={{Journal of KIISE}},\n    volume={{47}},\n    issue={{6}},\n    publisher={The Korean Institute of Information Scientists and Engineers},\n    year={2020},\n    ISSN={{2383-630X}},\n    pages={577-586},\n    url={http://www.dbpia.co.kr/journal/articleDetail?nodeId=NODE09353166}}\n", "homepage": "https://korquad.github.io/", "license": "CC BY-ND 2.0 KR", "features": {"id": {"dtype": "string", "id": null, "_type": "Value"}, "title": {"dtype": "string", "id": null, "_type": "Value"}, "context": {"dtype": "string", "id": null, "_type": "Value"}, "question": {"dtype": "string", "id": null, "_type": "Value"}, "answer": {"text": {"dtype": "string", "id": null, "_type": "Value"}, "answer_start": {"dtype": "int32", "id": null, "_type": "Value"}, "html_answer_start": {"dtype": "int32", "id": null, "_type": "Value"}}, "url": {"dtype": "string", "id": null, "_type": "Value"}, "raw_html": {"dtype": "string", "id": null, "_type": "Value"}}, "post_processed": null, "supervised_keys": null, "builder_name": "squad_kor_v2", "config_name": "squad_kor_v2", "version": {"version_str": "2.1.0", "description": null, "major": 2, "minor": 1, "patch": 0}, "splits": {"train": {"name": "train", "num_bytes": 17983434492, "num_examples": 83486, "dataset_name": "squad_kor_v2"}, "validation": {"name": "validation", "num_bytes": 2230543100, "num_examples": 10165, "dataset_name": "squad_kor_v2"}}, "download_checksums": {"https://github.com/korquad/korquad.github.io/raw/master/dataset/KorQuAD_2.1/train/KorQuAD_2.1_train_00.zip": {"num_bytes": 96161084, "checksum": "98918d10e3e08bf6b34b50d17cd7f7438d5a577a8089d02698d16a151424a36a"}, "https://github.com/korquad/korquad.github.io/raw/master/dataset/KorQuAD_2.1/train/KorQuAD_2.1_train_01.zip": {"num_bytes": 92163603, "checksum": "0a8a59ee82e92e9509c5dbf7d98a31c007a3693afb818e37c60ddacf7f48c4b3"}, "https://github.com/korquad/korquad.github.io/raw/master/dataset/KorQuAD_2.1/train/KorQuAD_2.1_train_02.zip": {"num_bytes": 91681447, "checksum": "7035a35daac0c210b4754fc6a2885442929754db35e33b40d7c912706c66b9bc"}, "https://github.com/korquad/korquad.github.io/raw/master/dataset/KorQuAD_2.1/train/KorQuAD_2.1_train_03.zip": {"num_bytes": 94792676, "checksum": "4a61272d13e535f73fa20f2d1619b895adb763d8fa7cf02d813b733e7f702562"}, "https://github.com/korquad/korquad.github.io/raw/master/dataset/KorQuAD_2.1/train/KorQuAD_2.1_train_04.zip": {"num_bytes": 94470762, "checksum": "35834a74b3486eaa32712c689bccaab0c841c3ee252560e754245d3ed89e1c3a"}, "https://github.com/korquad/korquad.github.io/raw/master/dataset/KorQuAD_2.1/train/KorQuAD_2.1_train_05.zip": {"num_bytes": 93427959, "checksum": "5ea9b2975451c5a67bc172690a56a6e7a9e87b4001d3d1d684cb1336958a3a3b"}, "https://github.com/korquad/korquad.github.io/raw/master/dataset/KorQuAD_2.1/train/KorQuAD_2.1_train_06.zip": {"num_bytes": 93224892, "checksum": "87872acd46c2a8291a176826ad7eb23f3a6cf1db05bb27566d2eac1199a9091b"}, "https://github.com/korquad/korquad.github.io/raw/master/dataset/KorQuAD_2.1/train/KorQuAD_2.1_train_07.zip": {"num_bytes": 92550803, "checksum": "a615c0ebba60fc9b55fa602973d504f76d0273592c22f63b7f202655c1bb10bf"}, "https://github.com/korquad/korquad.github.io/raw/master/dataset/KorQuAD_2.1/train/KorQuAD_2.1_train_08.zip": {"num_bytes": 93684404, "checksum": "fa3955e23eab859819990edde3dd23308740cf94c3839fb538f30b1126117a39"}, "https://github.com/korquad/korquad.github.io/raw/master/dataset/KorQuAD_2.1/train/KorQuAD_2.1_train_09.zip": {"num_bytes": 94028022, "checksum": "b3b7ec508fbacaf6a5c12065e1d061cbfd8990bf2ae4c940a0a8d841294c2c1c"}, "https://github.com/korquad/korquad.github.io/raw/master/dataset/KorQuAD_2.1/train/KorQuAD_2.1_train_10.zip": {"num_bytes": 93432479, "checksum": "b7e8e44e43ec63514265e2202f73a4a6ce46f7226cc5662efc6a2ab92161a462"}, "https://github.com/korquad/korquad.github.io/raw/master/dataset/KorQuAD_2.1/train/KorQuAD_2.1_train_11.zip": {"num_bytes": 94500610, "checksum": "f6483e1e4b2577603e4fc881ec1651ca2ea5764a4b0f7e5eb59007ed9cc4bbae"}, "https://github.com/korquad/korquad.github.io/raw/master/dataset/KorQuAD_2.1/train/KorQuAD_2.1_train_12.zip": {"num_bytes": 99301520, "checksum": "84c4b6391a07bc1fdcc70d7194bda0e65edc796ae9b4e184a58c58d6973af7ad"}, "https://github.com/korquad/korquad.github.io/raw/master/dataset/KorQuAD_2.1/dev/KorQuAD_2.1_dev_00.zip": {"num_bytes": 93536216, "checksum": "4a0b25f896f333dc470e87b83cef874a9f7ea9a3df4c83f5ce8d5de6d71b07db"}, "https://github.com/korquad/korquad.github.io/raw/master/dataset/KorQuAD_2.1/dev/KorQuAD_2.1_dev_01.zip": {"num_bytes": 56806828, "checksum": "bf76fe7c684409151f92eacc56d551d0471477c47959b916c002ae39666caf59"}}, "download_size": 1373763305, "post_processing_size": null, "dataset_size": 20213977592, "size_in_bytes": 21587740897}}