{"default": {"description": "ASNQ is a dataset for answer sentence selection derived from\nGoogle Natural Questions (NQ) dataset (Kwiatkowski et al. 2019).\n", "citation": "@article{garg2019tanda,\n    title={TANDA: Transfer and Adapt Pre-Trained Transformer Models for Answer Sentence Selection},\n    author={Siddhant Garg and Thuy Vu and Alessandro Moschitti},\n    year={2019},\n    eprint={1911.04118},\n}\n", "homepage": "https://github.com/alexa/wqa_tanda#answer-sentence-natural-questions-asnq", "license": "", "features": {"sentence1": {"dtype": "string", "id": null, "_type": "Value"}, "sentence2": {"dtype": "string", "id": null, "_type": "Value"}, "label": {"dtype": "int32", "id": null, "_type": "Value"}}, "post_processed": null, "supervised_keys": null, "builder_name": "asnq", "config_name": "default", "version": {"version_str": "1.0.0", "description": null, "major": 1, "minor": 0, "patch": 0}, "splits": {"train": {"name": "train", "num_bytes": 3570276712, "num_examples": 20377568, "dataset_name": "asnq"}, "validation": {"name": "validation", "num_bytes": 164052391, "num_examples": 930062, "dataset_name": "asnq"}}, "download_checksums": {"https://wqa-public.s3.amazonaws.com/tanda-aaai-2020/data/asnq.tar": {"num_bytes": 3563857920, "checksum": "4211d3e507e7cfa345a9eea3c5222b7d79fd963cf27407555c5558c37344ddf1"}}, "download_size": 3563857920, "post_processing_size": null, "dataset_size": 3734329103, "size_in_bytes": 7298187023}}
